ATdispatcher/__init__.py
ATdispatcher/core.py
atdispatcher-1.0.1.dist-info/licenses/LICENSE
atdispatcher-1.0.1.dist-info/METADATA
atdispatcher-1.0.1.dist-info/WHEEL
atdispatcher-1.0.1.dist-info/top_level.txt
atdispatcher-1.0.1.dist-info/RECORD
